jostar/__init__.py
jostar/algorithms/__init__.py
jostar/algorithms/_aco.py
jostar/algorithms/_de.py
jostar/algorithms/_ga.py
jostar/algorithms/_lrs.py
jostar/algorithms/_nsga2.py
jostar/algorithms/_pso.py
jostar/algorithms/_sa.py
jostar/algorithms/_sbs.py
jostar/algorithms/_sfs.py
jostar/functions/__init__.py
jostar/functions/ff.py
jostar/functions/ff_nsga2.py
jostar/metrics/__init__.py
jostar/metrics/_metrics.py
jostar/utils/__init__.py
jostar/utils/_base_feature_selector.py
jostar/utils/_hyperparameter_tuner.py
jostar-0.0.4.dist-info/LICENSE
jostar-0.0.4.dist-info/METADATA
jostar-0.0.4.dist-info/WHEEL
jostar-0.0.4.dist-info/top_level.txt
jostar-0.0.4.dist-info/RECORD
