Metadata-Version: 2.1
Name: jostar
Version: 0.0.4
Summary: Feature Selection Module for Data Sciences in Python
Home-page: UNKNOWN
Author: Amirhossein Hassanzadeh
Author-email: ah7557@rit.edu
License: UNKNOWN
Keywords: particle swarm,multi-objective,metaheuristics,optimization,genetic algorithm,ant colony,sequential search,differential evolution,feature-selection
Platform: UNKNOWN
Classifier: Programming Language :: Python :: 3.6
Classifier: License :: OSI Approved :: MIT License
Classifier: Operating System :: OS Independent
Requires-Dist: sklearn
Requires-Dist: matplotlib
Requires-Dist: pathos
Requires-Dist: scipy
Requires-Dist: seaborn
Provides-Extra: dev
Requires-Dist: pytest (>=3.6) ; extra == 'dev'
